{
  "created_at": "2026-06-23T10:12:48+00:00",
  "research": {
    "created_at": "2026-06-23T10:12:48+00:00",
    "research_bias": "ALLOW_SHORT_OR_RISK_OFF",
    "scenario": "Cautious",
    "signal_quality": "D",
    "signal_timing": "Data-Blocked",
    "final_score": 35.0,
    "allow_long": false,
    "allow_short": false,
    "reasons": [
      "positive_24h_momentum",
      "synthetic_or_fallback_data_source"
    ]
  },
  "trading_signal": {
    "signal": "NONE",
    "confidence": 0,
    "reasons": [
      "synthetic_or_fallback_data_no_signal"
    ]
  },
  "data_health": {
    "created_at": "2026-06-23T10:12:48+00:00",
    "status": "UNHEALTHY",
    "allow_trading": false,
    "problems": [
      "fallback_data_source_blocks_trading",
      "synthetic_data_source_blocks_trading"
    ],
    "warnings": [],
    "source_type": "synthetic_fallback",
    "data_quality": "synthetic",
    "is_synthetic": true,
    "is_fallback": true,
    "candle_count": 120,
    "latest_candle_time": "2026-06-23T09:00:00+00:00"
  },
  "risk": {
    "created_at": "2026-06-23T10:12:48+00:00",
    "status": "BLOCK_NEW_POSITION",
    "allow_new_position": false,
    "daily_pnl_r": -1.0,
    "weekly_pnl_r": -1.0,
    "consecutive_losses": 1,
    "drawdown_r": -1.0,
    "problems": [
      "max_drawdown_proxy_breached"
    ],
    "calculation_mode": "time_based_exit_time"
  },
  "final_decision": "BLOCK_DATA_HEALTH",
  "allow_order_intent": false,
  "direction": "NONE",
  "confidence": 0,
  "reasons": [
    "data_health_disallows_trading",
    "fallback_data_source_blocks_trading",
    "synthetic_data_source_blocks_trading"
  ]
}
